pdbprocessor/__init__.py
pdbprocessor/app.py
pdbprocessor/appinfo.py
pdbprocessor/interface.py
pdbprocessor/pdbprocessor.py
pdbprocessor/processor.py
pdbprocessor/setup.py
pdbprocessor-0.0.2.dist-info/LICENSE.txt
pdbprocessor-0.0.2.dist-info/METADATA
pdbprocessor-0.0.2.dist-info/WHEEL
pdbprocessor-0.0.2.dist-info/top_level.txt
pdbprocessor-0.0.2.dist-info/RECORD
