Metadata-Version: 2.1
Name: pdbprocessor
Version: 0.0.2
Summary: Simple PDB data extraction program
Home-page: https://github.com/igik20/pdbprocessor
Author: Igor Trujnara
Author-email: itrujnara@wp.pl
License: UNKNOWN
Project-URL: Bug Tracker, https://github.com/igik20/pdbprocessor/issues
Platform: UNKNOWN
Classifier: Programming Language :: Python :: 3
Classifier: License :: OSI Approved :: MIT License
Classifier: Operating System :: OS Independent
Requires-Python: >=3.6
License-File: LICENSE.txt
